Crea_pdf/Functions.py
Crea_pdf/__init__.py
Crea_pdf-0.0.4.dist-info/METADATA
Crea_pdf-0.0.4.dist-info/WHEEL
Crea_pdf-0.0.4.dist-info/top_level.txt
Crea_pdf-0.0.4.dist-info/RECORD
