Metadata-Version: 2.1
Name: Crea-pdf
Version: 0.0.4
Summary: Librería para crear pdf e incluir contenido en ella
Home-page: https://github.com/EstCarlos
Author: Carlos Soto De Dios
Author-email: 1106419@est.intec.edu.do
License: MIT
Requires-Dist: reportlab
